stepmania_to_sqlite/__init__.py
stepmania_to_sqlite/cli.py
stepmania_to_sqlite/utils.py
stepmania_to_sqlite-0.4.dist-info/LICENSE
stepmania_to_sqlite-0.4.dist-info/METADATA
stepmania_to_sqlite-0.4.dist-info/WHEEL
stepmania_to_sqlite-0.4.dist-info/entry_points.txt
stepmania_to_sqlite-0.4.dist-info/top_level.txt
stepmania_to_sqlite-0.4.dist-info/RECORD
