Metadata-Version: 2.1
Name: stepmania-to-sqlite
Version: 0.4
Summary: Save data about your Stepmania library to a SQLite database
Home-page: https://github.com/rixx/stepmania-to-sqlite
Author: Tobias Kunze
Author-email: r@rixx.de
License: Apache License, Version 2.0
Project-URL: Source, https://github.com/rixx/stepmania-to-sqlite
Project-URL: Issues, https://github.com/rixx/stepmania-to-sqlite/issues
Keywords: stepmania dance sqlite export dogsheep
Platform: UNKNOWN
Classifier: Development Status :: 5 - Production/Stable
Classifier: Environment :: Console
Classifier: License :: OSI Approved
Classifier: License :: OSI Approved :: Apache Software License
Classifier: Programming Language :: Python :: 3
Classifier: Programming Language :: Python :: 3.6
Classifier: Programming Language :: Python :: 3.7
Classifier: Topic :: Database
Requires-Dist: beautifulsoup4 (~=4.8)
Requires-Dist: click
Requires-Dist: python-dateutil
Requires-Dist: requests
Requires-Dist: sqlite-utils (~=2.4.4)
Requires-Dist: tqdm (~=4.36)
